chord_extractor/__init__.py
chord_extractor/base.py
chord_extractor/converters.py
chord_extractor/outputs.py
chord_extractor/version.py
chord_extractor/_lib/nnls-chroma.so
chord_extractor/extractors/__init__.py
chord_extractor/extractors/chordino.py
chord_extractor-0.1.2.dist-info/LICENSE
chord_extractor-0.1.2.dist-info/METADATA
chord_extractor-0.1.2.dist-info/WHEEL
chord_extractor-0.1.2.dist-info/top_level.txt
chord_extractor-0.1.2.dist-info/RECORD
