Metadata-Version: 2.1
Name: chord-extractor
Version: 0.1.2
Summary: Python library for extracting chords from multiple sound file formats
Home-page: https://github.com/ohollo/chord-extractor
Author: Oliver Holloway
Author-email: oholloway.consulting@gmail.com
License: UNKNOWN
Platform: UNKNOWN
Classifier: Programming Language :: Python :: 3
Classifier: License :: OSI Approved :: GNU General Public License v2 (GPLv2)
Classifier: Operating System :: OS Independent
Requires-Python: >=3.6,<3.10
License-File: LICENSE
Requires-Dist: librosa
Requires-Dist: vamp
